{
  "id": "sukabumi_kota",
  "nama": "Kota Sukabumi",
  "status_data": "measured",
  "harga": {
    "historis": [
      {
        "minggu": "2025-W30",
        "rp": 40000
      },
      {
        "minggu": "2025-W31",
        "rp": 37600
      },
      {
        "minggu": "2025-W32",
        "rp": 34000
      },
      {
        "minggu": "2025-W33",
        "rp": 34000
      },
      {
        "minggu": "2025-W34",
        "rp": 34000
      },
      {
        "minggu": "2025-W35",
        "rp": 37450
      },
      {
        "minggu": "2025-W36",
        "rp": 51250
      },
      {
        "minggu": "2025-W37",
        "rp": 51250
      },
      {
        "minggu": "2025-W38",
        "rp": 51250
      },
      {
        "minggu": "2025-W39",
        "rp": 51250
      },
      {
        "minggu": "2025-W40",
        "rp": 52750
      },
      {
        "minggu": "2025-W41",
        "rp": 53750
      },
      {
        "minggu": "2025-W42",
        "rp": 53750
      },
      {
        "minggu": "2025-W43",
        "rp": 53750
      },
      {
        "minggu": "2025-W44",
        "rp": 52250
      },
      {
        "minggu": "2025-W45",
        "rp": 50000
      },
      {
        "minggu": "2025-W46",
        "rp": 50000
      },
      {
        "minggu": "2025-W47",
        "rp": 50000
      },
      {
        "minggu": "2025-W48",
        "rp": 50000
      },
      {
        "minggu": "2025-W49",
        "rp": 52500
      },
      {
        "minggu": "2025-W50",
        "rp": 52500
      },
      {
        "minggu": "2025-W51",
        "rp": 52500
      },
      {
        "minggu": "2025-W52",
        "rp": 52500
      },
      {
        "minggu": "2026-W01",
        "rp": 47100
      },
      {
        "minggu": "2026-W02",
        "rp": 45750
      },
      {
        "minggu": "2026-W03",
        "rp": 45750
      },
      {
        "minggu": "2026-W04",
        "rp": 45750
      },
      {
        "minggu": "2026-W05",
        "rp": 40250
      },
      {
        "minggu": "2026-W06",
        "rp": 32000
      },
      {
        "minggu": "2026-W07",
        "rp": 32000
      },
      {
        "minggu": "2026-W08",
        "rp": 32000
      },
      {
        "minggu": "2026-W09",
        "rp": 32000
      },
      {
        "minggu": "2026-W10",
        "rp": 42500
      },
      {
        "minggu": "2026-W11",
        "rp": 42500
      },
      {
        "minggu": "2026-W12",
        "rp": 42500
      },
      {
        "minggu": "2026-W13",
        "rp": 42500
      },
      {
        "minggu": "2026-W14",
        "rp": 42500
      },
      {
        "minggu": "2026-W15",
        "rp": 42500
      },
      {
        "minggu": "2026-W16",
        "rp": 42500
      },
      {
        "minggu": "2026-W17",
        "rp": 42500
      },
      {
        "minggu": "2026-W18",
        "rp": 42500
      },
      {
        "minggu": "2026-W19",
        "rp": 45000
      },
      {
        "minggu": "2026-W20",
        "rp": 45000
      },
      {
        "minggu": "2026-W21",
        "rp": 45000
      },
      {
        "minggu": "2026-W22",
        "rp": 45500
      },
      {
        "minggu": "2026-W23",
        "rp": 47500
      },
      {
        "minggu": "2026-W24",
        "rp": 47500
      },
      {
        "minggu": "2026-W25",
        "rp": 47500
      },
      {
        "minggu": "2026-W26",
        "rp": 47500
      },
      {
        "minggu": "2026-W27",
        "rp": 42100
      },
      {
        "minggu": "2026-W28",
        "rp": 38500
      },
      {
        "minggu": "2026-W29",
        "rp": 38500
      }
    ],
    "forecast": [
      {
        "minggu": "2026-W30",
        "rp": 43510,
        "lo": 38069,
        "hi": 48724
      },
      {
        "minggu": "2026-W31",
        "rp": 49796,
        "lo": 41401,
        "hi": 57532
      },
      {
        "minggu": "2026-W32",
        "rp": 50816,
        "lo": 41647,
        "hi": 60434
      },
      {
        "minggu": "2026-W33",
        "rp": 51341,
        "lo": 40072,
        "hi": 62046
      },
      {
        "minggu": "2026-W34",
        "rp": 49888,
        "lo": 39419,
        "hi": 62299
      },
      {
        "minggu": "2026-W35",
        "rp": 46156,
        "lo": 34325,
        "hi": 57621
      },
      {
        "minggu": "2026-W36",
        "rp": 45729,
        "lo": 32414,
        "hi": 58165
      },
      {
        "minggu": "2026-W37",
        "rp": 43878,
        "lo": 28945,
        "hi": 57712
      },
      {
        "minggu": "2026-W38",
        "rp": 42272,
        "lo": 26933,
        "hi": 57947
      },
      {
        "minggu": "2026-W39",
        "rp": 39809,
        "lo": 24229,
        "hi": 56245
      },
      {
        "minggu": "2026-W40",
        "rp": 39917,
        "lo": 23162,
        "hi": 56071
      },
      {
        "minggu": "2026-W41",
        "rp": 40460,
        "lo": 23776,
        "hi": 57207
      }
    ],
    "mape_pct": null,
    "keyakinan": null
  },
  "pasokan_mingguan": [
    {
      "minggu": "2026-W30",
      "ton": 0.0
    },
    {
      "minggu": "2026-W31",
      "ton": 0.0
    },
    {
      "minggu": "2026-W32",
      "ton": 0.0
    },
    {
      "minggu": "2026-W33",
      "ton": 0.1
    },
    {
      "minggu": "2026-W34",
      "ton": 0.1
    },
    {
      "minggu": "2026-W35",
      "ton": 0.2
    },
    {
      "minggu": "2026-W36",
      "ton": 0.3
    },
    {
      "minggu": "2026-W37",
      "ton": 0.3
    },
    {
      "minggu": "2026-W38",
      "ton": 0.4
    },
    {
      "minggu": "2026-W39",
      "ton": 0.4
    },
    {
      "minggu": "2026-W40",
      "ton": 0.4
    },
    {
      "minggu": "2026-W41",
      "ton": 0.3
    },
    {
      "minggu": "2026-W42",
      "ton": 0.3
    },
    {
      "minggu": "2026-W43",
      "ton": 0.3
    },
    {
      "minggu": "2026-W44",
      "ton": 0.2
    },
    {
      "minggu": "2026-W45",
      "ton": 0.2
    }
  ]
}